{
 "1": {
  "Hireling Description": "Fire Arrow",
  "Code": "farw"
 },
 "2": {
  "Hireling Description": "Cold Arrow",
  "Code": "carw"
 },
 "3": {
  "Hireling Description": "Combat",
  "Code": "comb"
 },
 "4": {
  "Hireling Description": "Defensive Auras",
  "Code": "def"
 },
 "5": {
  "Hireling Description": "Offensive Auras",
  "Code": "off"
 },
 "6": {
  "Hireling Description": "Fire Spells",
  "Code": "fire"
 },
 "7": {
  "Hireling Description": "Cold Spells",
  "Code": "cold"
 },
 "8": {
  "Hireling Description": "Lightning Spells",
  "Code": "ltng"
 }
}