{
 "1": {
  "Hit Class": "Hand To Hand",
  "Code": "hth"
 },
 "2": {
  "Hit Class": "One Hand Swing vs. Small",
  "Code": "1hss"
 },
 "3": {
  "Hit Class": "One Hand Swing vs. Large",
  "Code": "1hsl"
 },
 "4": {
  "Hit Class": "Two Hand Swing vs. Small",
  "Code": "2hss"
 },
 "5": {
  "Hit Class": "Two Hand Swing vs. Large",
  "Code": "2hsl"
 },
 "6": {
  "Hit Class": "One Hand Thrust",
  "Code": "1ht"
 },
 "7": {
  "Hit Class": "Two Hand Thrust",
  "Code": "2ht"
 },
 "8": {
  "Hit Class": "Club",
  "Code": "club"
 },
 "9": {
  "Hit Class": "Staff",
  "Code": "staf"
 },
 "10": {
  "Hit Class": "Bow",
  "Code": "bow"
 },
 "11": {
  "Hit Class": "Crossbow",
  "Code": "xbow"
 },
 "12": {
  "Hit Class": "Claw",
  "Code": "claw"
 },
 "13": {
  "Hit Class": "Overlay",
  "Code": "over"
 }
}