{
 "0": {
  "name": "Beast",
  "itype1": "armo",
  "itype2": "weap",
  "itype3": "misc"
 },
 "1": {
  "name": "Eagle",
  "itype1": "armo",
  "itype2": "weap",
  "itype3": "misc"
 },
 "2": {
  "name": "Raven",
  "itype1": "armo",
  "itype2": "weap",
  "itype3": "misc"
 },
 "3": {
  "name": "Viper",
  "itype1": "armo",
  "itype2": "weap",
  "itype3": "misc"
 },
 "4": {
  "name": "GhoulRI",
  "itype1": "armo",
  "itype2": "weap",
  "itype3": "misc"
 },
 "5": {
  "name": "Skull",
  "itype1": "armo",
  "itype2": "weap",
  "itype3": "misc"
 },
 "6": {
  "name": "Blood",
  "itype1": "armo",
  "itype2": "weap",
  "itype3": "misc"
 },
 "7": {
  "name": "Dread",
  "itype1": "armo",
  "itype2": "weap",
  "itype3": "misc"
 },
 "8": {
  "name": "Doom",
  "itype1": "armo",
  "itype2": "weap",
  "itype3": "misc"
 },
 "9": {
  "name": "Grim",
  "itype1": "armo",
  "itype2": "weap",
  "itype3": "misc"
 },
 "10": {
  "name": "Bone",
  "itype1": "armo",
  "itype2": "weap",
  "itype3": "misc"
 },
 "11": {
  "name": "Death",
  "itype1": "armo",
  "itype2": "weap",
  "itype3": "misc"
 },
 "12": {
  "name": "Shadow",
  "itype1": "armo",
  "itype2": "weap",
  "itype3": "misc"
 },
 "13": {
  "name": "Storm",
  "itype1": "armo",
  "itype2": "weap",
  "itype3": "misc"
 },
 "14": {
  "name": "Rune",
  "itype1": "armo",
  "itype2": "weap",
  "itype3": "misc"
 },
 "15": {
  "name": "PlagueRI",
  "itype1": "armo",
  "itype2": "weap",
  "itype3": "misc"
 },
 "16": {
  "name": "Stone",
  "itype1": "armo",
  "itype2": "weap",
  "itype3": "misc"
 },
 "17": {
  "name": "Wraithra",
  "itype1": "armo",
  "itype2": "weap",
  "itype3": "misc"
 },
 "18": {
  "name": "Spirit",
  "itype1": "armo",
  "itype2": "rod"
 },
 "19": {
  "name": "Storm",
  "itype1": "armo",
  "itype2": "weap"
 },
 "20": {
  "name": "Demon",
  "itype1": "armo",
  "itype2": "weap"
 },
 "21": {
  "name": "Cruel",
  "itype1": "armo",
  "itype2": "weap"
 },
 "22": {
  "name": "Empyrion",
  "itype1": "rod"
 },
 "23": {
  "name": "Bramble",
  "itype1": "armo",
  "itype2": "weap"
 },
 "24": {
  "name": "Pain",
  "itype1": "armo",
  "itype2": "weap"
 },
 "25": {
  "name": "Loath",
  "itype1": "armo",
  "itype2": "weap"
 },
 "26": {
  "name": "Glyph",
  "itype1": "armo",
  "itype2": "weap"
 },
 "27": {
  "name": "Imp",
  "itype1": "armo",
  "itype2": "weap"
 },
 "28": {
  "name": "Fiendra",
  "itype1": "armo",
  "itype2": "weap"
 },
 "29": {
  "name": "Hailstone",
  "itype1": "armo",
  "itype2": "weap"
 },
 "30": {
  "name": "Gale",
  "itype1": "armo",
  "itype2": "weap"
 },
 "31": {
  "name": "Dire",
  "itype1": "armo",
  "itype2": "weap"
 },
 "32": {
  "name": "Soul",
  "itype1": "armo",
  "itype2": "weap"
 },
 "33": {
  "name": "Brimstone",
  "itype1": "armo",
  "itype2": "weap"
 },
 "34": {
  "name": "Corpse",
  "itype1": "armo",
  "itype2": "weap"
 },
 "35": {
  "name": "Carrion",
  "itype1": "armo",
  "itype2": "weap"
 },
 "36": {
  "name": "Holocaust",
  "itype1": "tors",
  "itype2": "helm",
  "itype3": "shld",
  "itype4": "swor",
  "itype5": "axe"
 },
 "37": {
  "name": "Havoc",
  "itype1": "armo",
  "itype2": "weap",
  "itype3": "misc"
 },
 "38": {
  "name": "Bitter",
  "itype1": "armo",
  "itype2": "weap",
  "itype3": "misc"
 },
 "39": {
  "name": "Entropy",
  "itype1": "ring",
  "itype2": "amul"
 },
 "40": {
  "name": "Chaos",
  "itype1": "ring",
  "itype2": "amul"
 },
 "41": {
  "name": "Order",
  "itype1": "ring",
  "itype2": "amul",
  "itype3": "scep"
 },
 "42": {
  "name": "Rule",
  "itype1": "rod"
 },
 "43": {
  "name": "Warp"
 },
 "44": {
  "name": "Rift"
 },
 "45": {
  "name": "Corruption",
  "itype1": "ring",
  "itype2": "amul"
 }
}